bulkdata/__init__.py
bulkdata/card.py
bulkdata/cli.py
bulkdata/deck.py
bulkdata/error.py
bulkdata/field.py
bulkdata/format.py
bulkdata/parse.py
bulkdata/util.py
bulkdata/pyNastran/__init__.py
bulkdata/pyNastran/bdf/__init__.py
bulkdata/pyNastran/bdf/field_writer_16.py
bulkdata/pyNastran/bdf/field_writer_8.py
bulkdata/pyNastran/bdf/cards/__init__.py
bulkdata/pyNastran/bdf/cards/utils.py
bulkdata/pyNastran/utils/__init__.py
bulkdata/pyNastran/utils/numpy_utils.py
bulkdata-0.6.1.dist-info/METADATA
bulkdata-0.6.1.dist-info/RECORD
bulkdata-0.6.1.dist-info/WHEEL
bulkdata-0.6.1.dist-info/top_level.txt
