Metadata-Version: 2.1
Name: bulkdata
Version: 0.6.1
Summary: Bulk Data Python Package makes it easy to create and manipulate bulk data files.
Home-page: https://github.com/marcodlk/bulkdata
Author: Marco T. de Lannoy Kobayashi
Author-email: mdlkdev@gmail.com
License: MIT license
Keywords: bulkdata
Platform: UNKNOWN
Classifier: Development Status :: 2 - Pre-Alpha
Classifier: Intended Audience :: Developers
Classifier: License :: OSI Approved :: MIT License
Classifier: Natural Language :: English
Classifier: Programming Language :: Python :: 3
Classifier: Programming Language :: Python :: 3.5
Classifier: Programming Language :: Python :: 3.6
Classifier: Programming Language :: Python :: 3.7
Classifier: Programming Language :: Python :: 3.8
Requires-Python: >=3.5
Requires-Dist: Click (>=7.0)
Requires-Dist: numpy
